{
  "resource_uri": "http://www.courtlistener.com/api/rest/v3/clusters/2512558/",
  "absolute_url": "/opinion/2512558/in-re-cozy-cove-marina-inc/",
  "panel": [],
  "non_participating_judges": [],
  "docket": "http://www.courtlistener.com/api/rest/v3/dockets/2379534/",
  "sub_opinions": [
    "http://www.courtlistener.com/api/rest/v3/opinions/2512558/"
  ],
  "judges": "James C. Dever",
  "date_created": "2014-10-30T23:44:38.974586Z",
  "date_modified": "2014-10-30T23:44:38.974586Z",
  "date_filed": "2007-11-05",
  "slug": "in-re-cozy-cove-marina-inc",
  "citation_id": 2485330,
  "case_name_short": "In Re Cozy Cove Marina, Inc.",
  "case_name": "In Re Cozy Cove Marina, Inc.",
  "case_name_full": "",
  "federal_cite_one": "521 F. Supp. 2d 504",
  "federal_cite_two": "",
  "federal_cite_three": "",
  "state_cite_one": "",
  "state_cite_two": "",
  "state_cite_three": "",
  "state_cite_regional": "",
  "specialty_cite_one": "",
  "scotus_early_cite": "",
  "lexis_cite": "",
  "westlaw_cite": "",
  "neutral_cite": "",
  "scdb_id": "",
  "scdb_decision_direction": null,
  "scdb_votes_majority": null,
  "scdb_votes_minority": null,
  "source": "L",
  "procedural_history": "",
  "attorneys": "",
  "nature_of_suit": "",
  "posture": "",
  "syllabus": "",
  "citation_count": 0,
  "precedential_status": "Published",
  "date_blocked": null,
  "blocked": false
}